html_reports/__init__.py
html_reports/reports.py
html_reports/templates/simple.html
html_reports-0.2.0.dist-info/LICENSE.txt
html_reports-0.2.0.dist-info/METADATA
html_reports-0.2.0.dist-info/WHEEL
html_reports-0.2.0.dist-info/top_level.txt
html_reports-0.2.0.dist-info/RECORD
