Metadata-Version: 2.1
Name: html-reports
Version: 0.2.0
Summary: Module to create static html reports
Home-page: https://github.com/villoro/html-reports
Author: Arnau Villoro
Author-email: arnau@villoro.com
License: MIT
Platform: UNKNOWN
Classifier: Intended Audience :: Developers
Classifier: Intended Audience :: Education
Classifier: Intended Audience :: Manufacturing
Classifier: Intended Audience :: Science/Research
Classifier: License :: OSI Approved :: MIT License
Classifier: Programming Language :: Python
Classifier: Programming Language :: Python :: 3.6
Requires-Dist: beautifulsoup4
Requires-Dist: jinja2
Requires-Dist: markdown
Requires-Dist: easydev
